turbodbc_arrow_support.cp36-win_amd64.pyd
turbodbc_intern.cp36-win_amd64.pyd
turbodbc_numpy_support.cp36-win_amd64.pyd
turbodbc/__init__.py
turbodbc/api_constants.py
turbodbc/connect.py
turbodbc/connection.py
turbodbc/constructors.py
turbodbc/cursor.py
turbodbc/data_types.py
turbodbc/exceptions.py
turbodbc/options.py
turbodbc-3.2.0.dist-info/LICENSE
turbodbc-3.2.0.dist-info/METADATA
turbodbc-3.2.0.dist-info/WHEEL
turbodbc-3.2.0.dist-info/top_level.txt
turbodbc-3.2.0.dist-info/RECORD
