Metadata-Version: 2.1
Name: turbodbc
Version: 3.2.0
Summary: turbodbc is a Python DB API 2.0 compatible ODBC driver
Home-page: https://github.com/blue-yonder/turbodbc
Author: Michael Koenig
Author-email: michael.koenig@blue-yonder.com
License: UNKNOWN
Platform: UNKNOWN
Classifier: Development Status :: 5 - Production/Stable
Classifier: Intended Audience :: Developers
Classifier: License :: OSI Approved :: MIT License
Classifier: Operating System :: POSIX :: Linux
Classifier: Operating System :: MacOS :: MacOS X
Classifier: Operating System :: Microsoft :: Windows
Classifier: Programming Language :: C++
Classifier: Programming Language :: Python :: 2.7
Classifier: Programming Language :: Python :: 3.4
Classifier: Programming Language :: Python :: 3.5
Classifier: Programming Language :: Python :: 3.6
Classifier: Programming Language :: Python :: Implementation :: CPython
Classifier: Topic :: Database
Requires-Dist: pybind11 (>=2.2.0)
Requires-Dist: six
Provides-Extra: arrow
Requires-Dist: pyarrow (<0.15,>=0.12) ; extra == 'arrow'
Provides-Extra: numpy
Requires-Dist: numpy (>=1.14.0) ; extra == 'numpy'
